LICENSE.txt
README.md
setup.cfg
setup.py
django_rtk_blue/__init__.py
django_rtk_blue/admin.py
django_rtk_blue/apps.py
django_rtk_blue/backends.py
django_rtk_blue/validators.py
django_rtk_blue.egg-info/PKG-INFO
django_rtk_blue.egg-info/SOURCES.txt
django_rtk_blue.egg-info/dependency_links.txt
django_rtk_blue.egg-info/not-zip-safe
django_rtk_blue.egg-info/requires.txt
django_rtk_blue.egg-info/top_level.txt
django_rtk_blue/mutations/__init__.py
django_rtk_blue/queries/__init__.py