Metadata-Version: 2.1
Name: django-rtk-blue
Version: 0.6.0
Summary: Extension of django-rtk that combines django-rtk-upfront, django-rtk-password and django-rtk-magic-link
Home-page: https://github.com/mnieber/django-rtk-home/blob/main/django-rtk-blue/README.md
Author: Maarten Nieber
Author-email: hallomaarten@yahoo.com
License: MIT
Platform: UNKNOWN
Requires-Python: >=3.6
License-File: LICENSE.txt
